ofxstatement_cd_tmb-1.2.4-py3.7-nspkg.pth
ofxstatement/plugins/tmbcd.py
ofxstatement_cd_tmb-1.2.4.dist-info/LICENSE
ofxstatement_cd_tmb-1.2.4.dist-info/METADATA
ofxstatement_cd_tmb-1.2.4.dist-info/WHEEL
ofxstatement_cd_tmb-1.2.4.dist-info/entry_points.txt
ofxstatement_cd_tmb-1.2.4.dist-info/namespace_packages.txt
ofxstatement_cd_tmb-1.2.4.dist-info/top_level.txt
ofxstatement_cd_tmb-1.2.4.dist-info/zip-safe
ofxstatement_cd_tmb-1.2.4.dist-info/RECORD
