Metadata-Version: 2.1
Name: ofxstatement-cd-tmb
Version: 1.2.4
Summary: OFXStatement plugin for TMB (DR Congo)
Home-page: https://github.com/BIZ4Africa/ofxstatement-cd-tmb
Author: Vincent Luba
Author-email: vincent@biz-4-africa.com
License: GPLv3
Download-URL: https://github.com/BIZ4Africa/ofxstatement-cd-tmb/archive/v1.0.zip
Keywords: ofx,banking,statement
Platform: UNKNOWN
Classifier: Development Status :: 4 - Beta
Classifier: Programming Language :: Python :: 3
Classifier: Natural Language :: English
Classifier: Topic :: Office/Business :: Financial :: Accounting
Classifier: Topic :: Utilities
Classifier: Environment :: Console
Classifier: Operating System :: OS Independent
Classifier: License :: OSI Approved :: GNU Affero General Public License v3
Requires-Dist: ofxstatement
Provides-Extra: test
Requires-Dist: freezegun ; extra == 'test'
Requires-Dist: pytest ; extra == 'test'
